{
  "project_info": {
    "project_number": "549327476774",
    "project_id": "maintenance-7cfcc",
    "storage_bucket": "maintenance-7cfcc.appspot.com"
  },
  "client": [
    {
      "client_info": {
        "mobilesdk_app_id": "1:549327476774:android:cf8bde62717db605b6aee7",
        "android_client_info": {
          "package_name": "com.maintenance.maintenance.info.maintenance"
        }
      },
      "oauth_client": [
        {
          "client_id": "549327476774-8916nkcdg3m7hgnu5o716ocds9l4n3tf.apps.googleusercontent.com",
          "client_type": 3
        }
      ],
      "api_key": [
        {
          "current_key": "AIzaSyBIN7UmHqdLdZqb4L8B8AoUxyOXQghHKHg"
        }
      ],
      "services": {
        "appinvite_service": {
          "other_platform_oauth_client": [
            {
              "client_id": "549327476774-8916nkcdg3m7hgnu5o716ocds9l4n3tf.apps.googleusercontent.com",
              "client_type": 3
            },
            {
              "client_id": "549327476774-8t8iths79sjrvgjoqkpe4ici61k09a0h.apps.googleusercontent.com",
              "client_type": 2,
              "ios_info": {
                "bundle_id": "com.maintenance.maintenance.info"
              }
            }
          ]
        }
      }
    }
  ],
  "configuration_version": "1"
}